{"@t":"2023-05-08T21:15:18.8896540Z","@mt":"HTTP {RequestMethod} {RequestPath} responded {StatusCode} in {Elapsed:0.0000} ms","@r":["632.6800"],"@l":"Error","@x":"MixedDreams.Application.Exceptions.BadRequestException: Email is already taken\r\n   at MixedDreams.Infrastructure.Services.AuthService.CreateUserAsync(IRegisterDto registerModel) in D:\\projects\\dotNet\\MixedDreams\\src\\MixedDreams.Infrastructure\\Services\\AuthService.cs:line 139\r\n   at MixedDreams.Infrastructure.Services.AuthService.RegisterCompanyAsync(CompanyRegisterRequest model) in D:\\projects\\dotNet\\MixedDreams\\src\\MixedDreams.Infrastructure\\Services\\AuthService.cs:line 103\r\n   at MixedDreams.WebAPI.Controllers.AuthController.RegisterCompany(CompanyRegisterRequest model) in D:\\projects\\dotNet\\MixedDreams\\src\\MixedDreams.WebAPI\\Controllers\\AuthController.cs:line 40\r\n   at Microsoft.AspNetCore.Mvc.Infrastructure.ActionMethodExecutor.TaskOfIActionResultExecutor.Execute(ActionContext actionContext, IActionResultTypeMapper mapper, ObjectMethodExecutor executor, Object controller, Object[] arguments)\r\n   at Microsoft.AspNetCore.Mvc.Infrastructure.ControllerActionInvoker.<InvokeActionMethodAsync>g__Awaited|12_0(ControllerActionInvoker invoker, ValueTask`1 actionResultValueTask)\r\n   at Microsoft.AspNetCore.Mvc.Infrastructure.ControllerActionInvoker.<InvokeNextActionFilterAsync>g__Awaited|10_0(ControllerActionInvoker invoker, Task lastTask, State next, Scope scope, Object state, Boolean isCompleted)\r\n   at Microsoft.AspNetCore.Mvc.Infrastructure.ControllerActionInvoker.Rethrow(ActionExecutedContextSealed context)\r\n   at Microsoft.AspNetCore.Mvc.Infrastructure.ControllerActionInvoker.Next(State& next, Scope& scope, Object& state, Boolean& isCompleted)\r\n   at Microsoft.AspNetCore.Mvc.Infrastructure.ControllerActionInvoker.<InvokeInnerFilterAsync>g__Awaited|13_0(ControllerActionInvoker invoker, Task lastTask, State next, Scope scope, Object state, Boolean isCompleted)\r\n   at Microsoft.AspNetCore.Mvc.Infrastructure.ResourceInvoker.<InvokeFilterPipelineAsync>g__Awaited|20_0(ResourceInvoker invoker, Task lastTask, State next, Scope scope, Object state, Boolean isCompleted)\r\n   at Microsoft.AspNetCore.Mvc.Infrastructure.ResourceInvoker.<InvokeAsync>g__Awaited|17_0(ResourceInvoker invoker, Task task, IDisposable scope)\r\n   at Microsoft.AspNetCore.Mvc.Infrastructure.ResourceInvoker.<InvokeAsync>g__Awaited|17_0(ResourceInvoker invoker, Task task, IDisposable scope)\r\n   at Microsoft.AspNetCore.Routing.EndpointMiddleware.<Invoke>g__AwaitRequestTask|6_0(Endpoint endpoint, Task requestTask, ILogger logger)\r\n   at Microsoft.AspNetCore.Authorization.AuthorizationMiddleware.Invoke(HttpContext context)\r\n   at Microsoft.AspNetCore.Authentication.AuthenticationMiddleware.Invoke(HttpContext context)\r\n   at Serilog.AspNetCore.RequestLoggingMiddleware.Invoke(HttpContext httpContext)","RequestMethod":"POST","RequestPath":"/api/auth/register/company","StatusCode":500,"Elapsed":632.68,"SourceContext":"Serilog.AspNetCore.RequestLoggingMiddleware","RequestId":"0HMQG158J5EF9:00000001","ConnectionId":"0HMQG158J5EF9"}
{"@t":"2023-05-08T21:15:18.9955805Z","@mt":"Something went wrong: {@exception}","@l":"Warning","exception":"Email is already taken","SourceContext":"MixedDreams.WebAPI.Middlewares.ExceptionMiddleware","RequestId":"0HMQG158J5EF9:00000001","RequestPath":"/api/auth/register/company","ConnectionId":"0HMQG158J5EF9"}
{"@t":"2023-05-08T21:15:20.0447912Z","@mt":"HTTP {RequestMethod} {RequestPath} responded {StatusCode} in {Elapsed:0.0000} ms","@r":["128.4826"],"@l":"Error","@x":"MixedDreams.Application.Exceptions.BadRequestException: Email is already taken\r\n   at MixedDreams.Infrastructure.Services.AuthService.CreateUserAsync(IRegisterDto registerModel) in D:\\projects\\dotNet\\MixedDreams\\src\\MixedDreams.Infrastructure\\Services\\AuthService.cs:line 139\r\n   at MixedDreams.Infrastructure.Services.AuthService.RegisterCompanyAsync(CompanyRegisterRequest model) in D:\\projects\\dotNet\\MixedDreams\\src\\MixedDreams.Infrastructure\\Services\\AuthService.cs:line 103\r\n   at MixedDreams.WebAPI.Controllers.AuthController.RegisterCompany(CompanyRegisterRequest model) in D:\\projects\\dotNet\\MixedDreams\\src\\MixedDreams.WebAPI\\Controllers\\AuthController.cs:line 40\r\n   at Microsoft.AspNetCore.Mvc.Infrastructure.ActionMethodExecutor.TaskOfIActionResultExecutor.Execute(ActionContext actionContext, IActionResultTypeMapper mapper, ObjectMethodExecutor executor, Object controller, Object[] arguments)\r\n   at Microsoft.AspNetCore.Mvc.Infrastructure.ControllerActionInvoker.<InvokeActionMethodAsync>g__Awaited|12_0(ControllerActionInvoker invoker, ValueTask`1 actionResultValueTask)\r\n   at Microsoft.AspNetCore.Mvc.Infrastructure.ControllerActionInvoker.<InvokeNextActionFilterAsync>g__Awaited|10_0(ControllerActionInvoker invoker, Task lastTask, State next, Scope scope, Object state, Boolean isCompleted)\r\n   at Microsoft.AspNetCore.Mvc.Infrastructure.ControllerActionInvoker.Rethrow(ActionExecutedContextSealed context)\r\n   at Microsoft.AspNetCore.Mvc.Infrastructure.ControllerActionInvoker.Next(State& next, Scope& scope, Object& state, Boolean& isCompleted)\r\n   at Microsoft.AspNetCore.Mvc.Infrastructure.ControllerActionInvoker.<InvokeInnerFilterAsync>g__Awaited|13_0(ControllerActionInvoker invoker, Task lastTask, State next, Scope scope, Object state, Boolean isCompleted)\r\n   at Microsoft.AspNetCore.Mvc.Infrastructure.ResourceInvoker.<InvokeFilterPipelineAsync>g__Awaited|20_0(ResourceInvoker invoker, Task lastTask, State next, Scope scope, Object state, Boolean isCompleted)\r\n   at Microsoft.AspNetCore.Mvc.Infrastructure.ResourceInvoker.<InvokeAsync>g__Awaited|17_0(ResourceInvoker invoker, Task task, IDisposable scope)\r\n   at Microsoft.AspNetCore.Mvc.Infrastructure.ResourceInvoker.<InvokeAsync>g__Awaited|17_0(ResourceInvoker invoker, Task task, IDisposable scope)\r\n   at Microsoft.AspNetCore.Routing.EndpointMiddleware.<Invoke>g__AwaitRequestTask|6_0(Endpoint endpoint, Task requestTask, ILogger logger)\r\n   at Microsoft.AspNetCore.Authorization.AuthorizationMiddleware.Invoke(HttpContext context)\r\n   at Microsoft.AspNetCore.Authentication.AuthenticationMiddleware.Invoke(HttpContext context)\r\n   at Serilog.AspNetCore.RequestLoggingMiddleware.Invoke(HttpContext httpContext)","RequestMethod":"POST","RequestPath":"/api/auth/register/company","StatusCode":500,"Elapsed":128.4826,"SourceContext":"Serilog.AspNetCore.RequestLoggingMiddleware","RequestId":"0HMQG158J5EF9:00000002","ConnectionId":"0HMQG158J5EF9"}
{"@t":"2023-05-08T21:15:20.0980142Z","@mt":"Something went wrong: {@exception}","@l":"Warning","exception":"Email is already taken","SourceContext":"MixedDreams.WebAPI.Middlewares.ExceptionMiddleware","RequestId":"0HMQG158J5EF9:00000002","RequestPath":"/api/auth/register/company","ConnectionId":"0HMQG158J5EF9"}
{"@t":"2023-05-08T21:15:21.0497229Z","@mt":"HTTP {RequestMethod} {RequestPath} responded {StatusCode} in {Elapsed:0.0000} ms","@r":["88.2848"],"@l":"Error","@x":"MixedDreams.Application.Exceptions.BadRequestException: Email is already taken\r\n   at MixedDreams.Infrastructure.Services.AuthService.CreateUserAsync(IRegisterDto registerModel) in D:\\projects\\dotNet\\MixedDreams\\src\\MixedDreams.Infrastructure\\Services\\AuthService.cs:line 139\r\n   at MixedDreams.Infrastructure.Services.AuthService.RegisterCompanyAsync(CompanyRegisterRequest model) in D:\\projects\\dotNet\\MixedDreams\\src\\MixedDreams.Infrastructure\\Services\\AuthService.cs:line 103\r\n   at MixedDreams.WebAPI.Controllers.AuthController.RegisterCompany(CompanyRegisterRequest model) in D:\\projects\\dotNet\\MixedDreams\\src\\MixedDreams.WebAPI\\Controllers\\AuthController.cs:line 40\r\n   at Microsoft.AspNetCore.Mvc.Infrastructure.ActionMethodExecutor.TaskOfIActionResultExecutor.Execute(ActionContext actionContext, IActionResultTypeMapper mapper, ObjectMethodExecutor executor, Object controller, Object[] arguments)\r\n   at Microsoft.AspNetCore.Mvc.Infrastructure.ControllerActionInvoker.<InvokeActionMethodAsync>g__Awaited|12_0(ControllerActionInvoker invoker, ValueTask`1 actionResultValueTask)\r\n   at Microsoft.AspNetCore.Mvc.Infrastructure.ControllerActionInvoker.<InvokeNextActionFilterAsync>g__Awaited|10_0(ControllerActionInvoker invoker, Task lastTask, State next, Scope scope, Object state, Boolean isCompleted)\r\n   at Microsoft.AspNetCore.Mvc.Infrastructure.ControllerActionInvoker.Rethrow(ActionExecutedContextSealed context)\r\n   at Microsoft.AspNetCore.Mvc.Infrastructure.ControllerActionInvoker.Next(State& next, Scope& scope, Object& state, Boolean& isCompleted)\r\n   at Microsoft.AspNetCore.Mvc.Infrastructure.ControllerActionInvoker.<InvokeInnerFilterAsync>g__Awaited|13_0(ControllerActionInvoker invoker, Task lastTask, State next, Scope scope, Object state, Boolean isCompleted)\r\n   at Microsoft.AspNetCore.Mvc.Infrastructure.ResourceInvoker.<InvokeFilterPipelineAsync>g__Awaited|20_0(ResourceInvoker invoker, Task lastTask, State next, Scope scope, Object state, Boolean isCompleted)\r\n   at Microsoft.AspNetCore.Mvc.Infrastructure.ResourceInvoker.<InvokeAsync>g__Awaited|17_0(ResourceInvoker invoker, Task task, IDisposable scope)\r\n   at Microsoft.AspNetCore.Mvc.Infrastructure.ResourceInvoker.<InvokeAsync>g__Awaited|17_0(ResourceInvoker invoker, Task task, IDisposable scope)\r\n   at Microsoft.AspNetCore.Routing.EndpointMiddleware.<Invoke>g__AwaitRequestTask|6_0(Endpoint endpoint, Task requestTask, ILogger logger)\r\n   at Microsoft.AspNetCore.Authorization.AuthorizationMiddleware.Invoke(HttpContext context)\r\n   at Microsoft.AspNetCore.Authentication.AuthenticationMiddleware.Invoke(HttpContext context)\r\n   at Serilog.AspNetCore.RequestLoggingMiddleware.Invoke(HttpContext httpContext)","RequestMethod":"POST","RequestPath":"/api/auth/register/company","StatusCode":500,"Elapsed":88.2848,"SourceContext":"Serilog.AspNetCore.RequestLoggingMiddleware","RequestId":"0HMQG158J5EF9:00000003","ConnectionId":"0HMQG158J5EF9"}
{"@t":"2023-05-08T21:15:21.1016600Z","@mt":"Something went wrong: {@exception}","@l":"Warning","exception":"Email is already taken","SourceContext":"MixedDreams.WebAPI.Middlewares.ExceptionMiddleware","RequestId":"0HMQG158J5EF9:00000003","RequestPath":"/api/auth/register/company","ConnectionId":"0HMQG158J5EF9"}
{"@t":"2023-05-08T21:15:21.8021450Z","@mt":"HTTP {RequestMethod} {RequestPath} responded {StatusCode} in {Elapsed:0.0000} ms","@r":["71.4560"],"@l":"Error","@x":"MixedDreams.Application.Exceptions.BadRequestException: Email is already taken\r\n   at MixedDreams.Infrastructure.Services.AuthService.CreateUserAsync(IRegisterDto registerModel) in D:\\projects\\dotNet\\MixedDreams\\src\\MixedDreams.Infrastructure\\Services\\AuthService.cs:line 139\r\n   at MixedDreams.Infrastructure.Services.AuthService.RegisterCompanyAsync(CompanyRegisterRequest model) in D:\\projects\\dotNet\\MixedDreams\\src\\MixedDreams.Infrastructure\\Services\\AuthService.cs:line 103\r\n   at MixedDreams.WebAPI.Controllers.AuthController.RegisterCompany(CompanyRegisterRequest model) in D:\\projects\\dotNet\\MixedDreams\\src\\MixedDreams.WebAPI\\Controllers\\AuthController.cs:line 40\r\n   at Microsoft.AspNetCore.Mvc.Infrastructure.ActionMethodExecutor.TaskOfIActionResultExecutor.Execute(ActionContext actionContext, IActionResultTypeMapper mapper, ObjectMethodExecutor executor, Object controller, Object[] arguments)\r\n   at Microsoft.AspNetCore.Mvc.Infrastructure.ControllerActionInvoker.<InvokeActionMethodAsync>g__Awaited|12_0(ControllerActionInvoker invoker, ValueTask`1 actionResultValueTask)\r\n   at Microsoft.AspNetCore.Mvc.Infrastructure.ControllerActionInvoker.<InvokeNextActionFilterAsync>g__Awaited|10_0(ControllerActionInvoker invoker, Task lastTask, State next, Scope scope, Object state, Boolean isCompleted)\r\n   at Microsoft.AspNetCore.Mvc.Infrastructure.ControllerActionInvoker.Rethrow(ActionExecutedContextSealed context)\r\n   at Microsoft.AspNetCore.Mvc.Infrastructure.ControllerActionInvoker.Next(State& next, Scope& scope, Object& state, Boolean& isCompleted)\r\n   at Microsoft.AspNetCore.Mvc.Infrastructure.ControllerActionInvoker.<InvokeInnerFilterAsync>g__Awaited|13_0(ControllerActionInvoker invoker, Task lastTask, State next, Scope scope, Object state, Boolean isCompleted)\r\n   at Microsoft.AspNetCore.Mvc.Infrastructure.ResourceInvoker.<InvokeFilterPipelineAsync>g__Awaited|20_0(ResourceInvoker invoker, Task lastTask, State next, Scope scope, Object state, Boolean isCompleted)\r\n   at Microsoft.AspNetCore.Mvc.Infrastructure.ResourceInvoker.<InvokeAsync>g__Awaited|17_0(ResourceInvoker invoker, Task task, IDisposable scope)\r\n   at Microsoft.AspNetCore.Mvc.Infrastructure.ResourceInvoker.<InvokeAsync>g__Awaited|17_0(ResourceInvoker invoker, Task task, IDisposable scope)\r\n   at Microsoft.AspNetCore.Routing.EndpointMiddleware.<Invoke>g__AwaitRequestTask|6_0(Endpoint endpoint, Task requestTask, ILogger logger)\r\n   at Microsoft.AspNetCore.Authorization.AuthorizationMiddleware.Invoke(HttpContext context)\r\n   at Microsoft.AspNetCore.Authentication.AuthenticationMiddleware.Invoke(HttpContext context)\r\n   at Serilog.AspNetCore.RequestLoggingMiddleware.Invoke(HttpContext httpContext)","RequestMethod":"POST","RequestPath":"/api/auth/register/company","StatusCode":500,"Elapsed":71.456,"SourceContext":"Serilog.AspNetCore.RequestLoggingMiddleware","RequestId":"0HMQG158J5EF9:00000004","ConnectionId":"0HMQG158J5EF9"}
{"@t":"2023-05-08T21:15:21.8523492Z","@mt":"Something went wrong: {@exception}","@l":"Warning","exception":"Email is already taken","SourceContext":"MixedDreams.WebAPI.Middlewares.ExceptionMiddleware","RequestId":"0HMQG158J5EF9:00000004","RequestPath":"/api/auth/register/company","ConnectionId":"0HMQG158J5EF9"}
{"@t":"2023-05-08T21:20:01.6142900Z","@mt":"Starting web application"}
{"@t":"2023-05-08T21:20:36.1867142Z","@mt":"Starting web application"}
